raphson_music_client/__init__.py
raphson_music_client/control.py
raphson_music_client/headless.py
raphson_music_client/lyrics.py
raphson_music_client/playlist.py
raphson_music_client/py.typed
raphson_music_client/track.py
raphson_music_client/util.py
raphson_music_client-1.2.0.dist-info/METADATA
raphson_music_client-1.2.0.dist-info/WHEEL
raphson_music_client-1.2.0.dist-info/RECORD
