Metadata-Version: 2.3
Name: raphson_music_client
Version: 1.2.0
Summary: Raphson music player API client
Project-URL: Homepage, https://codeberg.org/raphson/music-client-python
Project-URL: Issues, https://codeberg.org/raphson/music-client-python/issues
Author-email: Robin Slot <robin@rslot.nl>
Classifier: Development Status :: 5 - Production/Stable
Classifier: Environment :: Console
Classifier: Framework :: AsyncIO
Classifier: Intended Audience :: Developers
Classifier: License :: OSI Approved :: GNU General Public License v3 (GPLv3)
Classifier: Natural Language :: English
Classifier: Operating System :: OS Independent
Classifier: Programming Language :: Python :: 3
Classifier: Topic :: Multimedia :: Sound/Audio
Classifier: Typing :: Typed
Requires-Python: >=3.11
Requires-Dist: aiohttp
